robust_deid/__init__.py
robust_deid/data_processing/__init__.py
robust_deid/data_processing/data_loader.py
robust_deid/deid/__init__.py
robust_deid/deid/text_deid.py
robust_deid/deid/utils.py
robust_deid/ner_datasets/__init__.py
robust_deid/ner_datasets/dataset_creator.py
robust_deid/ner_datasets/dataset_splitter.py
robust_deid/ner_datasets/span_fixer.py
robust_deid/ner_datasets/span_validation.py
robust_deid/ner_datasets/dataset_builder/__init__.py
robust_deid/ner_datasets/dataset_builder/dataset.py
robust_deid/ner_datasets/dataset_builder/sentence_dataset.py
robust_deid/ner_datasets/dataset_builder/labels/__init__.py
robust_deid/ner_datasets/dataset_builder/labels/mismatch_error.py
robust_deid/ner_datasets/dataset_builder/labels/ner_predict_token_labels.py
robust_deid/ner_datasets/dataset_builder/labels/ner_token_labels.py
robust_deid/ner_datasets/distribution/__init__.py
robust_deid/ner_datasets/distribution/dataset_splits.py
robust_deid/ner_datasets/distribution/ner_distribution.py
robust_deid/ner_datasets/distribution/print_distribution.py
robust_deid/ner_datasets/preprocessing/__init__.py
robust_deid/ner_datasets/preprocessing/preprocessing_loader.py
robust_deid/ner_datasets/preprocessing/sentencizers/__init__.py
robust_deid/ner_datasets/preprocessing/sentencizers/note_sentencizer.py
robust_deid/ner_datasets/preprocessing/sentencizers/spacy_sentencizer.py
robust_deid/ner_datasets/preprocessing/tokenizers/__init__.py
robust_deid/ner_datasets/preprocessing/tokenizers/clinical_spacy_tokenizer.py
robust_deid/ner_datasets/preprocessing/tokenizers/core_nlp_tokenizer.py
robust_deid/ner_datasets/preprocessing/tokenizers/spacy_tokenizer.py
robust_deid/ner_datasets/preprocessing/tokenizers/abbreviations/__init__.py
robust_deid/ner_datasets/preprocessing/tokenizers/abbreviations/medical_abbreviations.txt
robust_deid/ner_datasets/preprocessing/tokenizers/utils/__init__.py
robust_deid/ner_datasets/preprocessing/tokenizers/utils/clean_regex.py
robust_deid-0.3.1.dist-info/LICENSE
robust_deid-0.3.1.dist-info/METADATA
robust_deid-0.3.1.dist-info/WHEEL
robust_deid-0.3.1.dist-info/entry_points.txt
robust_deid-0.3.1.dist-info/top_level.txt
robust_deid-0.3.1.dist-info/RECORD
