Metadata-Version: 2.1
Name: robust-deid
Version: 0.3.1
Summary: A package to remove private information (PHI/PII) from medical notes.
Home-page: https://github.com/obi-ml-public/ehr_deidentification
Author: Prajwal Kailas, Max Homilius, Shinichi Goto
Author-email: prajwal967@gmail.com
License: MIT
Project-URL: Bug Tracker, https://github.com/obi-ml-public/ehr_deidentification/issues
Project-URL: Demo, https://huggingface.co/spaces/obi/Medical-Note-Deidentification
Project-URL: OBI-RoBERTa De-ID, https://huggingface.co/obi/deid_roberta_i2b2
Project-URL: OBI-ClinicalBERT De-ID Model, https://huggingface.co/obi/deid_bert_i2b2
Keywords: ehr deidentification medical phi transformers nlp ner
Platform: any
Classifier: Development Status :: 4 - Beta
Classifier: Programming Language :: Python
Requires-Python: >=3.7
License-File: LICENSE
